kstflow/__init__.py
kstflow/dataset.py
kstflow/labels.py
kstflow/spine.py
kstflow-0.1.44.dist-info/METADATA
kstflow-0.1.44.dist-info/WHEEL
kstflow-0.1.44.dist-info/top_level.txt
kstflow-0.1.44.dist-info/RECORD
