Metadata-Version: 2.2
Name: kstflow
Version: 0.1.44
Summary: KST AI Utilities for medical datasets
Home-page: https://kst.buu.ac.th
Author: Watcharaphong Yookwan
Author-email: kst@informatics.buu.ac.th
Classifier: Programming Language :: Python :: 3
Classifier: Operating System :: OS Independent
Requires-Python: >=3.6
Requires-Dist: requests
Requires-Dist: tqdm
Requires-Dist: matplotlib
Requires-Dist: pillow
Requires-Dist: opencv-python
Requires-Dist: tensorflow-cpu
Requires-Dist: numpy
Dynamic: author
Dynamic: author-email
Dynamic: classifier
Dynamic: description
Dynamic: description-content-type
Dynamic: home-page
Dynamic: requires-dist
Dynamic: requires-python
Dynamic: summary
